{
  "name": "WatchMovieToken",
  "symbol": "WMT",
  "description": "WatchMovieToken is a Solana SPL token created for demo and community use.",
  "image": "https://raw.githubusercontent.com/yunhungo/yunhungo_assets/main/tokens/wmt/IconWatchMovieToken.png",
  "uri": "https://raw.githubusercontent.com/yunhungo/yunhungo_assets/main/tokens/wmt/metadata.json",
  "seller_fee_basis_points": 0,
  "creators": [
    {
      "address": "CCFN2x3aMnk79DX7mCsfrnWs1zmoortTva3apXg7Ay7x",
      "verified": true,
      "share": 100
    }
  ],
  "extensions": {
    "website": "https://github.com/yunhungo",
    "twitter": "https://x.com/yunhungo"
  }
}